task2/f1_fsm.sv
module f1_fsm (
    input logic clk,
    input logic en,
    input logic rst,
    output logic[7:0] dout
);

always_ff @(posedge clk, posedge rst)
if(rst) dout <= 7'b0;
else begin
    if(en) dout <= dout == 255 ? 0 : {dout[6:0], 1'b1};
    else dout <= dout;
end
endmodule

task2/f1_fsm.vcd
$version Generated by VerilatedVcd $end
$date Tue Nov  8 15:32:25 2022 $end
$timescale 1ps $end

 $scope module TOP $end
  $var wire  1 # clk $end
  $var wire  8 & dout [7:0] $end
  $var wire  1 $ en $end
  $var wire  1 % rst $end
  $scope module f1_fsm $end
   $var wire  1 # clk $end
   $var wire  8 & dout [7:0] $end
   $var wire  1 $ en $end
   $var wire  1 % rst $end
  $upscope $end
 $upscope $end
$enddefinitions $end


#0
1#
0$
1%
b00000000 &
#1
0#
#2
1#
1$
#3
0#
#4
1#
0$
#5
0#
#6
1#
0%
#7
0#
#8
1#
#9
0#
#10
1#
#11
0#
#12
1#
#13
0#
#14
1#
#15
0#
#16
1#
#17
0#
#18
1#
#19
0#
#20
1#
#21
0#
#22
1#
#23
0#
#24
1#
#25
0#
#26
1#
#27
0#
#28
1#
#29
0#
#30
1#
#31
0#
#32
1#
#33
0#
#34
1#
#35
0#
#36
1#
#37
0#
#38
1#
#39
0#
#40
1#
#41
0#
#42
1#
#43
0#
#44
1#
#45
0#
#46
1#
#47
0#
#48
1#
1$
#49
0#
#50
1#
0$
b00000001 &
#51
0#
#52
1#
#53
0#
#54
1#
#55
0#
#56
1#
#57
0#
#58
1#
#59
0#
#60
1#
#61
0#
#62
1#
#63
0#
#64
1#
#65
0#
#66
1#
#67
0#
#68
1#
#69
0#
#70
1#
#71
0#
#72
1#
#73
0#
#74
1#
#75
0#
#76
1#
#77
0#
#78
1#
#79
0#
#80
1#
#81
0#
#82
1#
#83
0#
#84
1#
#85
0#
#86
1#
1$
#87
0#
#88
1#
0$
b00000011 &
#89
0#
#90
1#
#91
0#
#92
1#
#93
0#
#94
1#
#95
0#
#96
1#
#97
0#
#98
1#
#99
0#
#100
1#
#101
0#
#102
1#
#103
0#
#104
1#
1$
#105
0#
#106
1#
0$
b00000111 &
#107
0#
#108
1#
#109
0#
#110
1#
#111
0#
#112
1#
#113
0#
#114
1#
#115
0#
#116
1#
#117
0#
#118
1#
#119
0#
#120
1#
#121
0#
#122
1#
1$
#123
0#
#124
1#
0$
b00001111 &
#125
0#
#126
1#
#127
0#
#128
1#
#129
0#
#130
1#
#131
0#
#132
1#
#133
0#
#134
1#
1$
#135
0#
#136
1#
0$
b00011111 &
#137
0#
#138
1#
#139
0#
#140
1#
#141
0#
#142
1#
#143
0#
#144
1#
#145
0#
#146
1#
#147
0#
#148
1#
#149
0#
#150
1#
#151
0#
#152
1#
#153
0#
#154
1#
#155
0#
#156
1#
#157
0#
#158
1#
#159
0#
#160
1#
#161
0#
#162
1#
#163
0#
#164
1#
1$
#165
0#
#166
1#
0$
b00111111 &
#167
0#
#168
1#
#169
0#
#170
1#
#171
0#
#172
1#
#173
0#
#174
1#
#175
0#
#176
1#
#177
0#
#178
1#
#179
0#
#180
1#
#181
0#
#182
1#
#183
0#
#184
1#
#185
0#
#186
1#
#187
0#
#188
1#
#189
0#
#190
1#
#191
0#
#192
1#
#193
0#
#194
1#
#195
0#
#196
1#
1$
#197
0#
#198
1#
0$
b01111111 &
#199
0#
#200
1#
#201
0#
#202
1#
#203
0#
#204
1#
#205
0#
#206
1#
#207
0#
#208
1#
#209
0#
#210
1#
#211
0#
#212
1#
#213
0#
#214
1#
#215
0#
#216
1#
#217
0#
#218
1#
#219
0#
#220
1#
#221
0#
#222
1#
1$
#223
0#
#224
1#
0$
b11111111 &
